Makefile
development.ini
requirements.txt
setup.cfg
setup.py
backrest/__init__.py
backrest/commands.py
backrest/models.py
backrest/testing.py
backrest/views.py
backrest/tests/dummy_talks.json
backrest/tests/test_appinfo.py
backrest/tests/test_models.py
backrest/tests/test_post_talks.py
halfnarp.egg-info/PKG-INFO
halfnarp.egg-info/SOURCES.txt
halfnarp.egg-info/dependency_links.txt
halfnarp.egg-info/entry_points.txt
halfnarp.egg-info/not-zip-safe
halfnarp.egg-info/requires.txt
halfnarp.egg-info/top_level.txt